clean_notebook/__init__.py
clean_notebook/__main__.py
clean_notebook/_version.py
clean_notebook/clean.py
clean_notebook-0.1.17.dist-info/METADATA
clean_notebook-0.1.17.dist-info/WHEEL
clean_notebook-0.1.17.dist-info/entry_points.txt
clean_notebook-0.1.17.dist-info/licenses/LICENSE.txt
clean_notebook-0.1.17.dist-info/RECORD
