Metadata-Version: 2.4
Name: clean-notebook
Version: 0.1.17
Summary: A simple package to clean Jupyter notebooks
Project-URL: Homepage, https://github.com/hoxbro/clean_notebook
Project-URL: Source, https://github.com/hoxbro/clean_notebook
Author: Simon Hansen
Maintainer: Simon Hansen
License-Expression: MIT
License-File: LICENSE.txt
Keywords: clean,jupyter,notebook
Classifier: License :: OSI Approved :: MIT License
Classifier: Operating System :: OS Independent
Classifier: Programming Language :: Python :: 3.8
Classifier: Programming Language :: Python :: 3.9
Classifier: Programming Language :: Python :: 3.10
Classifier: Programming Language :: Python :: 3.11
Classifier: Programming Language :: Python :: 3.12
Classifier: Programming Language :: Python :: 3.13
Requires-Python: >=3.8
Provides-Extra: dev
Requires-Dist: black; extra == 'dev'
Requires-Dist: hatch; extra == 'dev'
Requires-Dist: mypy; extra == 'dev'
Requires-Dist: pre-commit; extra == 'dev'
Requires-Dist: pytest; extra == 'dev'
Requires-Dist: ruff; extra == 'dev'
